odoo/addons/web_confirm_duplicate/README.rst
odoo/addons/web_confirm_duplicate/__init__.py
odoo/addons/web_confirm_duplicate/__manifest__.py
odoo/addons/web_confirm_duplicate/i18n/web_confirm_duplicate.pot
odoo/addons/web_confirm_duplicate/readme/CONTRIBUTORS.rst
odoo/addons/web_confirm_duplicate/readme/DESCRIPTION.rst
odoo/addons/web_confirm_duplicate/readme/USAGE.rst
odoo/addons/web_confirm_duplicate/static/description/icon.png
odoo/addons/web_confirm_duplicate/static/description/index.html
odoo/addons/web_confirm_duplicate/static/src/js/basic_view.js
odoo/addons/web_confirm_duplicate/static/src/js/form_controller.js
odoo/addons/web_confirm_duplicate/templates/assets.xml
odoo13_addon_web_confirm_duplicate-13.0.1.0.1.dist-info/METADATA
odoo13_addon_web_confirm_duplicate-13.0.1.0.1.dist-info/WHEEL
odoo13_addon_web_confirm_duplicate-13.0.1.0.1.dist-info/top_level.txt
odoo13_addon_web_confirm_duplicate-13.0.1.0.1.dist-info/RECORD
